setup.py
cns/__init__.py
cns.recipe.zmysqlda.egg-info/PKG-INFO
cns.recipe.zmysqlda.egg-info/SOURCES.txt
cns.recipe.zmysqlda.egg-info/dependency_links.txt
cns.recipe.zmysqlda.egg-info/entry_points.txt
cns.recipe.zmysqlda.egg-info/namespace_packages.txt
cns.recipe.zmysqlda.egg-info/not-zip-safe
cns.recipe.zmysqlda.egg-info/requires.txt
cns.recipe.zmysqlda.egg-info/top_level.txt
cns/recipe/__init__.py
cns/recipe/zmysqlda/__init__.py
