Metadata-Version: 1.0
Name: cns.recipe.zmysqlda
Version: 2.0.8
Summary: Recipe for installing ZMySQLDA
Home-page: http://corenet-int.com
Author: Radim Novotny
Author-email: radim.novotny@corenet.cz
License: GPL
Keywords: buildout
Platform: UNKNOWN
Classifier: Framework :: Plone
Classifier: Framework :: Zope2
Classifier: Programming Language :: Python
Classifier: Topic :: Software Development :: Libraries :: Python Modules
